ops241/__init__.py
ops241/cli.py
ops241/radar.py
ops241_radar-0.0.4.dist-info/LICENCE
ops241_radar-0.0.4.dist-info/METADATA
ops241_radar-0.0.4.dist-info/WHEEL
ops241_radar-0.0.4.dist-info/entry_points.txt
ops241_radar-0.0.4.dist-info/top_level.txt
ops241_radar-0.0.4.dist-info/RECORD
