Metadata-Version: 2.1
Name: ops241-radar
Version: 0.0.4
Summary: OPS241 Radar
Home-page: https://github.com/sthysel/ops241
Author: sthysel
Author-email: sthysel@gmail.com
License: MIT
Platform: UNKNOWN
Classifier: License :: OSI Approved :: MIT License
Classifier: Operating System :: OS Independent
Classifier: Development Status :: 4 - Beta
Classifier: Operating System :: Unix
Classifier: Operating System :: POSIX
Classifier: Programming Language :: Python :: 3
Classifier: Topic :: Utilities
Requires-Dist: click
Requires-Dist: pyserial
